cn2int/__init__.py
cn2int/cn2int.py
cn2int/performance.py
cn2int-0.2.3.dist-info/METADATA
cn2int-0.2.3.dist-info/WHEEL
cn2int-0.2.3.dist-info/top_level.txt
cn2int-0.2.3.dist-info/RECORD
