Metadata-Version: 2.1
Name: cn2int
Version: 0.2.3
Summary: Conversion bettwen Chinese number and integer/float
Home-page: https://github.com/citysu/cn2int
Author: Hecheng Su
Author-email: 2215523266@qq.com
License: UNKNOWN
Platform: UNKNOWN
Classifier: Programming Language :: Python :: 3
Requires-Python: >=3
